febraban_barcode/__init__.py
febraban_barcode/base64.py
febraban_barcode/constants.py
febraban_barcode/functions.py
febraban_barcode/image.py
febraban_barcode/retorno.py
febraban_barcode-0.3.0.dist-info/LICENSE
febraban_barcode-0.3.0.dist-info/METADATA
febraban_barcode-0.3.0.dist-info/WHEEL
febraban_barcode-0.3.0.dist-info/RECORD
