Metadata-Version: 2.1
Name: febraban-barcode
Version: 0.3.0
Summary: Implementação em python do layout padrão de arrecadação/recebimento com utilização do código de barras da Febraban.
License: MIT
Author: William Sampaio
Author-email: 1997wbms@gmail.com
Requires-Python: >=3.11,<4.0
Classifier: License :: OSI Approved :: MIT License
Classifier: Programming Language :: Python :: 3
Classifier: Programming Language :: Python :: 3.11
Classifier: Programming Language :: Python :: 3.12
Requires-Dist: pillow (>=10.0.0,<11.0.0)
Requires-Dist: python-barcode (>=0.15.1,<0.16.0)
Project-URL: Código, https://github.com/WilliamSampaio/febraban_barcode
Project-URL: Documentação, https://febraban-barcode.readthedocs.io/
